{
  "project_info": {
    "project_number": "677476833710",
    "project_id": "tsfsocialmedia-66073",
    "storage_bucket": "tsfsocialmedia-66073.appspot.com"
  },
  "client": [
    {
      "client_info": {
        "mobilesdk_app_id": "1:677476833710:android:eac6552bd29c38021a903f",
        "android_client_info": {
          "package_name": "com.example.tsfsocialmedia"
        }
      },
      "oauth_client": [
        {
          "client_id": "677476833710-dfdsdmde4p2fmiq6k6pnieafha9np797.apps.googleusercontent.com",
          "client_type": 3
        }
      ],
      "api_key": [
        {
          "current_key": "AIzaSyAuu2lesYw115mKQhBezdvAPJZZgSq4bhE"
        }
      ],
      "services": {
        "appinvite_service": {
          "other_platform_oauth_client": [
            {
              "client_id": "677476833710-dfdsdmde4p2fmiq6k6pnieafha9np797.apps.googleusercontent.com",
              "client_type": 3
            }
          ]
        }
      }
    }
  ],
  "configuration_version": "1"
}